lco_etc/__init__.py
lco_etc/_version.py
lco_etc/etc.py
lco_etc-0.0.1.dist-info/LICENSE
lco_etc-0.0.1.dist-info/METADATA
lco_etc-0.0.1.dist-info/WHEEL
lco_etc-0.0.1.dist-info/top_level.txt
lco_etc-0.0.1.dist-info/RECORD
