Metadata-Version: 2.1
Name: lco_etc
Version: 0.0.1
Author-email: Braden Garretson <bgarrets@purdue.edu>
License: MIT License
Project-URL: Source Code, https://github.com/bradengarretson/lco_etc
Classifier: Development Status :: 4 - Beta
Classifier: License :: OSI Approved :: MIT License
Classifier: Intended Audience :: Developers
Classifier: Intended Audience :: Science/Research
Classifier: Operating System :: OS Independent
Classifier: Programming Language :: Python
Requires-Python: >=3.9
License-File: LICENSE
Provides-Extra: dev
Requires-Dist: asv ==0.6.3 ; extra == 'dev'
Requires-Dist: jupyter ; extra == 'dev'
Requires-Dist: pre-commit ; extra == 'dev'
Requires-Dist: pytest ; extra == 'dev'
Requires-Dist: pytest-cov ; extra == 'dev'
Requires-Dist: ruff ; extra == 'dev'
